MANIFEST.in
README.rst
setup.py
html2data/__init__.py
html2data.egg-info/PKG-INFO
html2data.egg-info/SOURCES.txt
html2data.egg-info/dependency_links.txt
html2data.egg-info/requires.txt
html2data.egg-info/top_level.txt
tests/__init__.py
tests/test_parse.py
tests/test_tree.py