Metadata-Version: 1.0
Name: html2data
Version: 0.4.3
Summary: A simple way to transform a HTML file or URL to structured data.
Home-page: https://github.com/dperezrada/html2data
Author: Daniel Perez Rada
Author-email: dperezrada@gmail.com
License: BSD
Keywords: html2data html data xpath crawler transform
Platform: UNKNOWN
Classifier: Development Status :: 3 - Alpha
Classifier: Topic :: Utilities
Classifier: Intended Audience :: Developers
Classifier: License :: OSI Approved :: BSD License
